pdemof/__init__.py
pdemof-0.1.0.dist-info/WHEEL
pdemof-0.1.0.dist-info/METADATA
pdemof-0.1.0.dist-info/RECORD
